[
  {
    "no_soal": 1,
    "paket": "A",
    "soal": "Dalam Surat Al-Hujurat Ayat 13, terdapat keterangan bahwa Allah SWT menciptakan dan menjadikan manusia terkelompok dalam beragam bangsa dan suku. Tujuannya ialah agar manusia...",
    "pilihan": {
      "A": "Saling bersaing kekayaan",
      "B": "Saling mengenal",
      "C": "Saling bermusuhan",
      "D": "Saling membanggakan nasab"
    },
    "kunci": "B"
  },
  {
    "no_soal": 2,
    "paket": "A",
    "soal": "Binatang, tumbuh-tumbuhan, dan seluruh makhluk yang ada di langit dan di bumi diciptakan oleh Allah. Asmaul Husna yang sesuai dengan pernyataan tersebut adalah...",
    "pilihan": {
      "A": "Al-Khaliq",
      "B": "Al-Quddus",
      "C": "Al-Malik",
      "D": "As-Salam"
    },
    "kunci": "A"
  },
  {
    "no_soal": 3,
    "paket": "A",
    "soal": "Dalam kehidupan manusia, Allah SWT melebihkan sebagian orang atas sebagian orang yang lain. Meskipun demikian, manusia yang lebih mulia di sisi Allah SWT adalah mereka yang...",
    "pilihan": {
      "A": "Lebih tinggi jabatannya",
      "B": "Lebih banyak hartanya",
      "C": "Lebih besar taqwanya",
      "D": "Lebih rupawan wajahnya"
    },
    "kunci": "C"
  },
  {
    "no_soal": 4,
    "paket": "A",
    "soal": "Salah seorang Rasul Ulul Azmi yang diutus kepada kaum Bani Rasib namun tidak semua kaumnya taat kepada Allah sehingga Allah menurunkan adzab-Nya dengan menumpahkan air bah adalah...",
    "pilihan": {
      "A": "Nabi Ibrahim a.s.",
      "B": "Nabi Musa a.s.",
      "C": "Nabi Isa a.s.",
      "D": "Nabi Nuh a.s."
    },
    "kunci": "D"
  },
  {
    "no_soal": 5,
    "paket": "A",
    "soal": "Terjemahkan arti ayat berikut ini: إِنَّ أَكْرَمَكُمْ عِنْدَ اللَّهِ أَتْقَكُم",
    "pilihan": {
      "A": "Sesungguhnya yang paling kaya di antara kamu adalah yang paling dermawan",
      "B": "Sesungguhnya yang paling kuat di antara kamu adalah yang paling berani",
      "C": "Sesungguhnya yang paling mulia di antara kamu di sisi Allah adalah orang yang paling bertakwa",
      "D": "Sesungguhnya Allah menyukai orang-orang yang berbuat kebaikan"
    },
    "kunci": "C"
  },
  {
    "no_soal": 6,
    "paket": "A",
    "soal": "Salah satu sifat yang wajib bagi Rasul adalah tabligh. Lawan dari sifat tabligh adalah Kitman, yang artinya...",
    "pilihan": {
      "A": "Dusta",
      "B": "Menyembunyikan",
      "C": "Bodoh",
      "D": "Khianat"
    },
    "kunci": "B"
  },
  {
    "no_soal": 7,
    "paket": "A",
    "soal": "Sebelum shalat, Arum membasuh muka, tangan, kepala, dan kaki sesuai urutan. Ia juga membaca niat. Yang dilakukan Arum adalah...",
    "pilihan": {
      "A": "Tayamum",
      "B": "Mandi Wajib",
      "C": "Istinja",
      "D": "Wudhu"
    },
    "kunci": "D"
  },
  {
    "no_soal": 8,
    "paket": "A",
    "soal": "Perpindahan Nabi Muhammad SAW bersama sebagian pengikutnya dari Makkah ke Madinah untuk menyelamatkan diri dari tekanan kaum kafir Quraisy Makkah disebut...",
    "pilihan": {
      "A": "Haji",
      "B": "Umrah",
      "C": "Hijrah",
      "D": "Jihad"
    },
    "kunci": "C"
  },
  {
    "no_soal": 9,
    "paket": "A",
    "soal": "Batasan waktu satu tahun atas kepemilikan harta yang wajib dikeluarkan zakatnya sesuai syariat adalah pengertian dari...",
    "pilihan": {
      "A": "Nisab",
      "B": "Haul",
      "C": "Fidiah",
      "D": "Kafarat"
    },
    "kunci": "B"
  },
  {
    "no_soal": 10,
    "paket": "A",
    "soal": "Dalam Ilmu Tajwid, hukum Idgham Bilaghunnah terjadi ketika Nun Mati atau Tanwin bertemu dengan huruf...",
    "pilihan": {
      "A": "Ya, Nun, Mim, Wau",
      "B": "Ba",
      "C": "Lam & Ra",
      "D": "Hamzah, Ha, Kho, Ain, Ghin, Ha"
    },
    "kunci": "C"
  },
  {
    "no_soal": 11,
    "paket": "A",
    "soal": "Sesungguhnya Kami (Allah) telah menciptakan manusia dalam bentuk yang sebaik-baiknya. Penggalan arti surat tersebut terdapat dalam ayat ke-4 dari surat...",
    "pilihan": {
      "A": "QS Al-Maun",
      "B": "QS Al-Fil",
      "C": "QS At-Tin",
      "D": "QS Al-Insyirah"
    },
    "kunci": "C"
  },
  {
    "no_soal": 12,
    "paket": "A",
    "soal": "Nama-nama Allah yang baik salah satunya adalah Al-Malik. Asmaul Husna ini memiliki arti...",
    "pilihan": {
      "A": "Allah Maha Pencipta",
      "B": "Allah Maharaja",
      "C": "Allah Maha Suci",
      "D": "Allah Maha Pemberi Keamanan"
    },
    "kunci": "B"
  },
  {
    "no_soal": 13,
    "paket": "A",
    "soal": "Guru memanggil Fulan untuk menceritakan kembali hasil pembelajaran di depan kelas. Dengan semangat dan senang hati, Fulan pun maju ke depan. Sikap Fulan tersebut mencerminkan sikap...",
    "pilihan": {
      "A": "Tawadhu",
      "B": "Percaya Diri",
      "C": "Sombong",
      "D": "Mandiri"
    },
    "kunci": "B"
  },
  {
    "no_soal": 14,
    "paket": "A",
    "soal": "Shalat dua rakaat yang dilakukan secara berjamaah pada waktu dzuhur di hari Jumat sebagai pengganti shalat dzuhur disebut...",
    "pilihan": {
      "A": "Shalat Idul Fitri",
      "B": "Shalat Jumat",
      "C": "Shalat Rawatib",
      "D": "Shalat Dhuha"
    },
    "kunci": "B"
  },
  {
    "no_soal": 15,
    "paket": "A",
    "soal": "Perhatikan potongan ayat berikut: وَهَذَا الْبَلَدِ الْأَمِينِ . Terjemahan yang tepat untuk ayat tersebut adalah...",
    "pilihan": {
      "A": "Demi buah Tin dan buah Zaitun",
      "B": "Dan demi bukit Sinai",
      "C": "Dan demi negeri (Makkah) yang aman ini",
      "D": "Bukankah Allah Hakim yang paling adil?",
      "E": ""
    },
    "kunci": "C"
  },
  {
    "no_soal": 16,
    "paket": "A",
    "soal": "Sifat-sifat wajib bagi Rasul membuat mereka senantiasa terjaga dari dosa. Salah satu sifat wajib bagi Rasul adalah Fatonah, yang artinya...",
    "pilihan": {
      "A": "Jujur",
      "B": "Dapat Dipercaya",
      "C": "Menyampaikan",
      "D": "Cerdas/Pandai"
    },
    "kunci": "D"
  },
  {
    "no_soal": 17,
    "paket": "A",
    "soal": "Perjanjian perdamaian yang terjadi antara Kaum Quraisy Makkah dan penduduk muslim Madinah yang mengakibatkan gencatan senjata disebut...",
    "pilihan": {
      "A": "Piagam Madinah",
      "B": "Perjanjian Aqabah",
      "C": "Perjanjian Hudaibiyah",
      "D": "Bai'at Ridwan"
    },
    "kunci": "C"
  },
  {
    "no_soal": 18,
    "paket": "A",
    "soal": "Penerima Zakat Fitrah ada 8 golongan yang telah ditentukan dalam Al-Qur'an. Orang yang berhak menerima zakat tersebut disebut dengan istilah...",
    "pilihan": {
      "A": "Muzakki",
      "B": "Mustahiq",
      "C": "Amil",
      "D": "Munfiq"
    },
    "kunci": "B"
  },
  {
    "no_soal": 19,
    "paket": "A",
    "soal": "Kadar yang harus dikeluarkan dalam zakat fitrah adalah satu sha'. Jika dikonversikan ke dalam satuan berat yang umum di Indonesia, jumlah tersebut setara dengan...",
    "pilihan": {
      "A": "1,5 Kg",
      "B": "2,0 Kg",
      "C": "2,5 Kg",
      "D": "5,0 Kg"
    },
    "kunci": "C"
  },
  {
    "no_soal": 20,
    "paket": "A",
    "soal": "Dalam Ilmu Tajwid, apabila Nun Mati atau Tanwin bertemu dengan huruf Wau (و), maka hukum bacaannya disebut...",
    "pilihan": {
      "A": "Idgham Bilaghunnah",
      "B": "Idgham Bighunnah",
      "C": "Iqlab",
      "D": "Izhar Halqi"
    },
    "kunci": "B"
  },
  {
    "no_soal": 21,
    "paket": "A",
    "soal": "Ciri-ciri orang yang mendustakan agama disebutkan dalam Al-Qur'an Surat Al-Maun. Salah satu ciri tersebut adalah menghardik...",
    "pilihan": {
      "A": "Orang tua",
      "B": "Anak Yatim",
      "C": "Fakir Miskin",
      "D": "Musafir"
    },
    "kunci": "B"
  },
  {
    "no_soal": 22,
    "paket": "A",
    "soal": "Allah SWT adalah Dzat yang tersucikan dari segala macam kekurangan dan cela. Asmaul Husna yang memiliki arti Allah Maha Suci adalah...",
    "pilihan": {
      "A": "Al-Malik",
      "B": "Al-Quddus",
      "C": "As-Salam",
      "D": "Al-Khaliq"
    },
    "kunci": "B"
  },
  {
    "no_soal": 23,
    "paket": "A",
    "soal": "Berkata apa adanya sesuai dengan kenyataan tanpa menambah atau mengurangi hal-hal yang lain adalah pengertian dari sikap...",
    "pilihan": {
      "A": "Amanah",
      "B": "Istiqomah",
      "C": "Jujur",
      "D": "Tawadhu"
    },
    "kunci": "C"
  },
  {
    "no_soal": 24,
    "paket": "A",
    "soal": "Hukum melaksanakan shalat Jumat bagi laki-laki muslim yang sudah memenuhi syarat wajibnya adalah...",
    "pilihan": {
      "A": "Sunnah Muakkad",
      "B": "Fardhu Kifayah",
      "C": "Fardhu A'in",
      "D": "Mubah"
    },
    "kunci": "C"
  },
  {
    "no_soal": 25,
    "paket": "A",
    "soal": "Terjemahkan arti ayat berikut ini: فَذَلِكَ الَّذِي يَدُعُ الْيَتِيمَ",
    "pilihan": {
      "A": "Tahukah kamu (orang) yang mendustakan agama?",
      "B": "Maka itulah orang yang menghardik anak yatim",
      "C": "Dan tidak mendorong memberi makan orang miskin",
      "D": "Maka celakalah bagi orang-orang yang shalat"
    },
    "kunci": "B"
  },
  {
    "no_soal": 26,
    "paket": "A",
    "soal": "Para Rasul memiliki sifat mustahil, yaitu sifat yang tidak mungkin ada pada diri mereka. Salah satu sifat mustahil bagi Rasul adalah 'Kidzib', yang artinya...",
    "pilihan": {
      "A": "Bohong/Dusta",
      "B": "Menyembunyikan",
      "C": "Bodoh",
      "D": "Khianat"
    },
    "kunci": "A"
  },
  {
    "no_soal": 27,
    "paket": "A",
    "soal": "Ahmad memberikan barang berharga kepada Amin sebagai bentuk penghargaan karena prestasi Amin yang rajin dan jujur. Pemberian semacam ini dalam Islam disebut...",
    "pilihan": {
      "A": "Sedekah",
      "B": "Hibah",
      "C": "Hadiah",
      "D": "Infaq"
    },
    "kunci": "C"
  },
  {
    "no_soal": 28,
    "paket": "A",
    "soal": "Pelaksanaan Ibadah Haji telah ditentukan waktunya dan tidak sah jika dilakukan di luar waktu tersebut. Puncak Ibadah Haji dilakukan pada bulan...",
    "pilihan": {
      "A": "Ramadhan",
      "B": "Syawal",
      "C": "Dzulhijjah",
      "D": "Muharram"
    },
    "kunci": "C"
  },
  {
    "no_soal": 29,
    "paket": "A",
    "soal": "Zakat fitrah wajib dikeluarkan pada bulan Ramadhan. Batas akhir waktu mengeluarkan zakat fitrah agar tetap dinilai sebagai zakat adalah...",
    "pilihan": {
      "A": "Awal bulan Ramadhan",
      "B": "Pertengahan Ramadhan",
      "C": "Menjelang shalat Idul Fitri",
      "D": "Setelah shalat Idul Fitri"
    },
    "kunci": "C"
  },
  {
    "no_soal": 30,
    "paket": "A",
    "soal": "Dalam Ilmu Tajwid, apabila terdapat Nun Mati atau Tanwin bertemu dengan huruf Alif (Hamzah), maka hukum bacaannya disebut...",
    "pilihan": {
      "A": "Iqlab",
      "B": "Ikhfa Haqiqi",
      "C": "Idgham Bighunnah",
      "D": "Idzhar Halqi"
    },
    "kunci": "D"
  },
  {
    "no_soal": 41,
    "paket": "A",
    "soal": "Orang yang mendapatkan keringanan dari Allah SWT untuk tidak melaksanakan puasa karena sakit menahun dan tidak kunjung sembuh, diwajibkan menggantinya dengan cara...",
    "pilihan": {
      "A": "Mengqadha puasa di hari lain",
      "B": "Membayar Fidyah",
      "C": "Membayar Kifarat",
      "D": "Melakukan Shalat Taubat"
    },
    "kunci": "B"
  },
  {
    "no_soal": 42,
    "paket": "A",
    "soal": "Golongan orang yang termasuk mustahiq zakat salah satunya adalah 'Amilin'. Arti dari Amilin adalah...",
    "pilihan": {
      "A": "Orang yang terlilit hutang",
      "B": "Orang yang baru masuk Islam",
      "C": "Orang yang dalam perjalanan",
      "D": "Orang yang mengurus/panitia zakat"
    },
    "kunci": "D"
  },
  {
    "no_soal": 43,
    "paket": "A",
    "soal": "Siti Zulaikha adalah wanita yang dikisahkan mengejar-ngejar seorang Nabi karena ketampanannya. Nabi tersebut adalah...",
    "pilihan": {
      "A": "Nabi Ibrahim a.s.",
      "B": "Nabi Musa a.s.",
      "C": "Nabi Yusuf a.s.",
      "D": "Nabi Muhammad SAW"
    },
    "kunci": "C"
  },
  {
    "no_soal": 44,
    "paket": "A",
    "soal": "Terjemahkan arti ayat berikut ini: لَمْ يَلِدْ وَلَمْ يُولَدْ",
    "pilihan": {
      "A": "Katakanlah: Dialah Allah, Yang Maha Esa",
      "B": "Allah adalah Tuhan yang bergantung kepada-Nya segala sesuatu",
      "C": "(Allah) tidak beranak dan tidak pula diperanakkan",
      "D": "Dan tidak ada seorangpun yang setara dengan Dia"
    },
    "kunci": "C"
  },
  {
    "no_soal": 45,
    "paket": "A",
    "soal": "Nabi Ayyub a.s. dikenal dengan kesabarannya yang luar biasa. Salah satu ujian berat yang diberikan Allah kepadanya adalah...",
    "pilihan": {
      "A": "Dimakan ikan paus",
      "B": "Dibakar hidup-hidup",
      "C": "Penyakit kulit bertahun-tahun",
      "D": "Banjir bandang"
    },
    "kunci": "C"
  },
  {
    "no_soal": 46,
    "paket": "A",
    "soal": "Setiap yang bernyawa pasti akan mati. Asmaul Husna yang memiliki arti Allah Maha Mematikan adalah...",
    "pilihan": {
      "A": "Al-Hayyu",
      "B": "Al-Mumit",
      "C": "Al-Qayyum",
      "D": "Al-Ahad"
    },
    "kunci": "B"
  },
  {
    "no_soal": 47,
    "paket": "A",
    "soal": "Tidak mengganggu orang lain yang berbeda agama ketika beribadah, serta tidak membeda-bedakan teman yang berbeda suku, merupakan contoh dari sikap...",
    "pilihan": {
      "A": "Qanaah",
      "B": "Tawadhu",
      "C": "Toleransi (Tasamuh)",
      "D": "Tawakal"
    },
    "kunci": "C"
  },
  {
    "no_soal": 48,
    "paket": "A",
    "soal": "Dalam kondisi tidak ada air atau karena sakit yang menghalangi terkena air, seseorang dibolehkan bersuci menggunakan debu/tanah yang suci. Cara bersuci ini disebut...",
    "pilihan": {
      "A": "Wudhu",
      "B": "Mandi Wajib",
      "C": "Istinja",
      "D": "Tayamum"
    },
    "kunci": "D"
  },
  {
    "no_soal": 49,
    "paket": "A",
    "soal": "Setiap bangun tidur, Arga selalu membersihkan dan merapikan kamar tidurnya sendiri tanpa disuruh orang tua. Sikap Arga menunjukkan perilaku...",
    "pilihan": {
      "A": "Jujur",
      "B": "Mandiri",
      "C": "Sederhana",
      "D": "Santun"
    },
    "kunci": "B"
  },
  {
    "no_soal": 50,
    "paket": "A",
    "soal": "Ciri-ciri orang munafik ada tiga. Salah satunya adalah apabila ia berjanji, maka ia...",
    "pilihan": {
      "A": "Berdusta",
      "B": "Berkhianat",
      "C": "Mengingkari",
      "D": "Melupakan"
    },
    "kunci": "C"
  },
  {
    "no_soal": 51,
    "paket": "A",
    "soal": "Allah SWT dapat melihat makhluk sekecil apapun di alam semesta, meskipun bersembunyi di tempat gelap. Hal ini karena Allah memiliki Asmaul Husna...",
    "pilihan": {
      "A": "As-Sami'",
      "B": "Al-Alim",
      "C": "Al-Khabir",
      "D": "Al-Bashir"
    },
    "kunci": "D"
  },
  {
    "no_soal": 52,
    "paket": "A",
    "soal": "Nabi yang diberi mukjizat berupa kekayaan melimpah, mengerti bahasa binatang, dan mampu memerintah bangsa jin adalah...",
    "pilihan": {
      "A": "Nabi Daud a.s.",
      "B": "Nabi Sulaiman a.s.",
      "C": "Nabi Musa a.s.",
      "D": "Nabi Ibrahim a.s."
    },
    "kunci": "B"
  },
  {
    "no_soal": 53,
    "paket": "A",
    "soal": "Nama-nama Allah yang baik salah satunya adalah Al-Ghaffur. Arti dari Al-Ghaffur adalah...",
    "pilihan": {
      "A": "Allah Maha Pengampun",
      "B": "Allah Maha Penyayang",
      "C": "Allah Maha Bijaksana",
      "D": "Allah Maha Perkasa"
    },
    "kunci": "A"
  },
  {
    "no_soal": 54,
    "paket": "A",
    "soal": "Di antara sikap terpuji adalah berani menanggung segala akibat atas apa yang dilakukannya. Sikap ini disebut...",
    "pilihan": {
      "A": "Jujur",
      "B": "Disiplin",
      "C": "Bertanggung Jawab",
      "D": "Toleransi"
    },
    "kunci": "C"
  },
  {
    "no_soal": 55,
    "paket": "A",
    "soal": "Di antara golongan yang berhak menerima zakat adalah musafir, yakni orang yang sedang melakukan perjalanan jauh (bukan untuk maksiat) dan kehabisan bekal. Golongan ini disebut...",
    "pilihan": {
      "A": "Sabilillah",
      "B": "Gharim",
      "C": "Muallaf",
      "D": "Ibnu Sabil"
    },
    "kunci": "D"
  },
  {
    "no_soal": 56,
    "paket": "A",
    "soal": "Shalat wajib yang dapat diqashar (diringkas jumlah rakaatnya) adalah shalat yang berjumlah 4 rakaat, yaitu...",
    "pilihan": {
      "A": "Subuh, Dhuhur, Asar",
      "B": "Dhuhur, Asar, Isya",
      "C": "Asar, Maghrib, Isya",
      "D": "Dhuhur, Maghrib, Isya"
    },
    "kunci": "B"
  },
  {
    "no_soal": 57,
    "paket": "A",
    "soal": "Zulaika diperintahkan ibunya untuk membeli bumbu masak ke warung. Zulaika pun melaksanakan perintahnya dengan senang hati tanpa membantah. Perilaku Zulaika mencerminkan sikap...",
    "pilihan": {
      "A": "Hemat dan Cermat",
      "B": "Sabar dan Tabah",
      "C": "Berbakti Kepada Orang Tua",
      "D": "Tolong Menolong"
    },
    "kunci": "C"
  },
  {
    "no_soal": 58,
    "paket": "A",
    "soal": "Dalam melaksanakan shalat dianjurkan membaca bacaan dengan baik. Manakah di antara berikut ini yang merupakan bacaan doa duduk di antara dua sujud?",
    "pilihan": {
      "A": "Subhana rabbiyal azhimi wabihamdih",
      "B": "Robbighfirlii warhamnii wajburnii warfa'nii...",
      "C": "Attahiyyatul mubarakaatus sholawatut thoyyibatu lillah",
      "D": "Subhana rabbiyal a'la wabihamdih"
    },
    "kunci": "B"
  },
  {
    "no_soal": 59,
    "paket": "A",
    "soal": "Allah tidak beranak dan tidak pula diperanakan. Asmaul Husna yang memiliki arti Allah Maha Esa adalah...",
    "pilihan": {
      "A": "Al-Ahad",
      "B": "As-Samad",
      "C": "Al-Khaliq",
      "D": "Al-Bari"
    },
    "kunci": "A"
  },
  {
    "no_soal": 60,
    "paket": "A",
    "soal": "Terjemahan yang tepat untuk ayat قُلْ اَعُوْذُ بِرَبِّ النَّاسِ adalah...",
    "pilihan": {
      "A": "Katakanlah: 'Aku berlindung kepada Tuhannya manusia'",
      "B": "Raja manusia",
      "C": "Sembahan manusia",
      "D": "Dari kejahatan (bisikan) syaitan yang biasa bersembunyi"
    },
    "kunci": "A"
  },
  {
    "no_soal": 61,
    "paket": "A",
    "soal": "Nabi Yusuf a.s. memiliki seorang adik kandung yang sangat disayanginya dan memiliki sifat baik hati. Siapakah nama adik Nabi Yusuf tersebut?",
    "pilihan": {
      "A": "Yahuda",
      "B": "Lawi",
      "C": "Bunyamin",
      "D": "Syam'un"
    },
    "kunci": "C"
  },
  {
    "no_soal": 1,
    "paket": "B",
    "soal": "Al-Kautsar adalah nama salah satu surat dalam Al-Qur'an. Arti dari kata Al-Kautsar adalah...",
    "pilihan": {
      "A": "Pembukaan",
      "B": "Pertolongan",
      "C": "Nikmat Yang Banyak",
      "D": "Waktu Dhuha"
    },
    "kunci": "C"
  },
  {
    "no_soal": 2,
    "paket": "B",
    "soal": "Allah SWT adalah Tuhan yang selalu mengayomi serta memberikan rasa damai bagi hamba-Nya. Kedamaian adalah simbol kebahagiaan seluruh umat manusia. Asmaul Husna yang sesuai dengan pernyataan tersebut adalah...",
    "pilihan": {
      "A": "Al-Mukmin",
      "B": "As-Salam",
      "C": "Al-Aziz",
      "D": "Al-Jabbar"
    },
    "kunci": "B"
  },
  {
    "no_soal": 3,
    "paket": "B",
    "soal": "Zainab memberikan sedekah tanpa mengharapkan imbalan apa pun atau pujian dari orang lain. Sikap Zainab tersebut mencerminkan sikap...",
    "pilihan": {
      "A": "Riya",
      "B": "Ujub",
      "C": "Ikhlas",
      "D": "Sombong"
    },
    "kunci": "C"
  },
  {
    "no_soal": 4,
    "paket": "B",
    "soal": "Dalam shalat, ketika melakukan gerakan sujud kita membaca doa...",
    "pilihan": {
      "A": "Subhana rabbiyal 'azhimi wabihamdih",
      "B": "Subhana rabbiyal a'la wabihamdih",
      "C": "Sami'allahu liman hamidah",
      "D": "Rabbana lakal hamdu"
    },
    "kunci": "B"
  },
  {
    "no_soal": 5,
    "paket": "B",
    "soal": "Utsman bin Affan mendapat gelar 'Dzunnurain' karena beliau menikahi dua puteri Rasulullah SAW. Arti dari Dzunnurain adalah...",
    "pilihan": {
      "A": "Pemilik dua cahaya",
      "B": "Pemisah antara yang hak dan batil",
      "C": "Pedang Allah yang terhunus",
      "D": "Gerbang ilmu"
    },
    "kunci": "A"
  },
  {
    "no_soal": 6,
    "paket": "B",
    "soal": "Perhatikan ayat berikut: الَّذِينَ هُمْ عَنْ صَلاتِهِمْ سَاهُونَ . Ayat tersebut merupakan bunyi Surat Al-Maun ayat ke...",
    "pilihan": {
      "A": "Keempat (4)",
      "B": "Kelima (5)",
      "C": "Keenam (6)",
      "D": "Ketujuh (7)"
    },
    "kunci": "B"
  },
  {
    "no_soal": 7,
    "paket": "B",
    "soal": "Qadar adalah ketentuan Allah SWT yang berlaku terhadap semua makhluk-Nya, namun masih bisa diubah (takdir muallaq) dengan adanya doa dan...",
    "pilihan": {
      "A": "Pasrah",
      "B": "Ikhtiar/Usaha",
      "C": "Qanaah",
      "D": "Keluh Kesah"
    },
    "kunci": "B"
  },
  {
    "no_soal": 8,
    "paket": "B",
    "soal": "Perilaku menghambur-hamburkan harta hanya untuk sekedar memenuhi kepuasan diri dan keinginan sesaat, termasuk cerminan dari sikap...",
    "pilihan": {
      "A": "Kikir",
      "B": "Dermawan",
      "C": "Boros (Tabzir)",
      "D": "Hemat"
    },
    "kunci": "C"
  },
  {
    "no_soal": 9,
    "paket": "B",
    "soal": "Cara yang sah untuk mensucikan diri dari hadas kecil (seperti buang air kecil atau buang angin) agar bisa melaksanakan shalat adalah dengan cara...",
    "pilihan": {
      "A": "Mandi Wajib",
      "B": "Istinja saja",
      "C": "Wudhu",
      "D": "Mandi biasa"
    },
    "kunci": "C"
  },
  {
    "no_soal": 10,
    "paket": "B",
    "soal": "Shalat sunnah yang dilakukan menjelang tengah hari, dimulai sejak matahari mulai naik (sepenggalah) dan terasa panas hingga menjelang waktu dzuhur, disebut shalat...",
    "pilihan": {
      "A": "Shalat Tahajud",
      "B": "Shalat Witir",
      "C": "Shalat Rawatib",
      "D": "Shalat Dhuha"
    },
    "kunci": "D"
  },
  {
    "no_soal": 11,
    "paket": "B",
    "soal": "Ali-Imran adalah nama salah satu surat dalam Al-Qur'an. Arti dari nama Ali-Imran adalah...",
    "pilihan": {
      "A": "Keluarga Nabi",
      "B": "Keluarga Imran",
      "C": "Para Wanita",
      "D": "Meja Hidangan"
    },
    "kunci": "B"
  },
  {
    "no_soal": 12,
    "paket": "B",
    "soal": "Allah adalah pemilik kerajaan yang di langit maupun di bumi. Asmaul Husna yang memiliki arti Allah Maha Merajai adalah...",
    "pilihan": {
      "A": "Al-Malik",
      "B": "Al-Ghaffar",
      "C": "Al-Hasib",
      "D": "Al-Hakim"
    },
    "kunci": "A"
  },
  {
    "no_soal": 13,
    "paket": "B",
    "soal": "Sikap yang harus dimiliki oleh seorang muslim adalah rendah hati, tidak sombong, dan menghargai orang lain. Dalam agama Islam, sikap rendah hati disebut...",
    "pilihan": {
      "A": "Qanaah",
      "B": "Tasamuh",
      "C": "Tawaduk",
      "D": "Taawun"
    },
    "kunci": "C"
  },
  {
    "no_soal": 14,
    "paket": "B",
    "soal": "Manakah di bawah ini yang merupakan potongan bacaan doa Tasyahud Awal?",
    "pilihan": {
      "A": "Robbighfirlii warhamnii wajburnii...",
      "B": "Attahiyyaatul mubaarokaatush sholawaatuth thoyyibaatu lillaah...",
      "C": "Subhanakallahumma wabihamdika...",
      "D": "Allahumma baid baini wa baina khotoyaya..."
    },
    "kunci": "B"
  },
  {
    "no_soal": 15,
    "paket": "B",
    "soal": "Sahabat Abu Bakar r.a. mendapatkan gelar kehormatan karena beliau selalu membenarkan peristiwa Isra' Mi'raj dan ucapan Rasulullah. Gelar tersebut adalah...",
    "pilihan": {
      "A": "Al-Faruq",
      "B": "As-Siddiq",
      "C": "Dzunnurain",
      "D": "Saifullah"
    },
    "kunci": "B"
  },
  {
    "no_soal": 16,
    "paket": "B",
    "soal": "Perhatikan ayat berikut: الَّذِينَ هُمْ يُرَاءُونَ . Ayat tersebut merupakan bunyi Surat Al-Maun ayat ke...",
    "pilihan": {
      "A": "Keempat (4)",
      "B": "Kelima (5)",
      "C": "Keenam (6)",
      "D": "Ketujuh (7)"
    },
    "kunci": "C"
  },
  {
    "no_soal": 17,
    "paket": "B",
    "soal": "Kematian atau ajal adalah ketentuan Allah yang sudah pasti dan tidak dapat dimajukan atau dimundurkan oleh manusia. Ketentuan yang tidak bisa diubah ini disebut...",
    "pilihan": {
      "A": "Takdir Muallaq",
      "B": "Takdir Mubram",
      "C": "Nasib",
      "D": "Ikhtiar"
    },
    "kunci": "B"
  },
  {
    "no_soal": 18,
    "paket": "B",
    "soal": "Dalam Surat Al-Maun dijelaskan celakalah orang yang shalat namun lalai, yaitu orang yang beribadah hanya karena ingin dipuji orang lain. Sikap ini disebut...",
    "pilihan": {
      "A": "Syirik",
      "B": "Munafik",
      "C": "Riya",
      "D": "Sum'ah"
    },
    "kunci": "C"
  },
  {
    "no_soal": 19,
    "paket": "B",
    "soal": "Berikut ini adalah contoh penyebab seseorang berhadas kecil yang mengharuskannya berwudhu kembali, yaitu...",
    "pilihan": {
      "A": "Meninggal dunia",
      "B": "Haid/Menstruasi",
      "C": "Keluar Mani",
      "D": "Buang Air Kecil/Besar"
    },
    "kunci": "D"
  },
  {
    "no_soal": 20,
    "paket": "B",
    "soal": "Nabi Ibrahim a.s. memiliki putra yang lahir dari pernikahannya dengan Siti Hajar. Putra beliau tersebut bernama...",
    "pilihan": {
      "A": "Nabi Ishaq a.s.",
      "B": "Nabi Ismail a.s.",
      "C": "Nabi Yusuf a.s.",
      "D": "Nabi Yakub a.s."
    },
    "kunci": "B"
  },
  {
    "no_soal": 21,
    "paket": "B",
    "soal": "Al-Baqarah adalah nama salah satu surat dalam Al-Qur'an dan merupakan surat terpanjang. Arti dari Al-Baqarah adalah...",
    "pilihan": {
      "A": "Keluarga Imran",
      "B": "Sapi Betina",
      "C": "Lebah",
      "D": "Wanita"
    },
    "kunci": "B"
  },
  {
    "no_soal": 22,
    "paket": "B",
    "soal": "Alam semesta yang indah dan luas adalah bukti dari keagungan Allah. Asmaul Husna yang berarti Allah Maha Agung adalah...",
    "pilihan": {
      "A": "Al-Kabir",
      "B": "Al-Aliyy",
      "C": "Al-'Azim",
      "D": "Al-Majid"
    },
    "kunci": "C"
  },
  {
    "no_soal": 23,
    "paket": "B",
    "soal": "Hari Senin Fulan ditugaskan menjadi petugas upacara. Ia datang tepat waktu, berseragam lengkap, dan melaksanakan tugas dengan baik. Sikap Fulan mencerminkan perilaku...",
    "pilihan": {
      "A": "Jujur",
      "B": "Disiplin",
      "C": "Hemat",
      "D": "Tawadhu"
    },
    "kunci": "B"
  },
  {
    "no_soal": 24,
    "paket": "B",
    "soal": "Perhatikan bacaan berikut: 'Allaahu akbar kabiiraw walhamdu lillaahi katsiira...'. Bacaan tersebut adalah bagian dari doa yang dibaca setelah Takbiratul Ihram, yaitu...",
    "pilihan": {
      "A": "Doa Qunut",
      "B": "Doa Iftitah",
      "C": "Doa I'tidal",
      "D": "Doa Tasyahud"
    },
    "kunci": "B"
  },
  {
    "no_soal": 25,
    "paket": "B",
    "soal": "Salah satu sahabat Nabi yang termasuk Khulafaur Rasyidin adalah Umar bin Khattab. Beliau mendapat gelar 'Al-Faruq' yang artinya...",
    "pilihan": {
      "A": "Singa Padang Pasir",
      "B": "Pemisah antara yang haq dan yang batil",
      "C": "Orang yang sangat jujur",
      "D": "Gerbang ilmu pengetahuan"
    },
    "kunci": "B"
  },
  {
    "no_soal": 26,
    "paket": "B",
    "soal": "Ayat 'Fawailul lil musholliin' (فَوَيْلٌ لِلْمُصَلِّينَ) adalah bunyi Surat Al-Maun ayat ke...",
    "pilihan": {
      "A": "Ke-3",
      "B": "Ke-4",
      "C": "Ke-5",
      "D": "Ke-6"
    },
    "kunci": "B"
  },
  {
    "no_soal": 27,
    "paket": "B",
    "soal": "Kematian, kelahiran, dan matahari terbit dari sebelah timur merupakan ketetapan Allah yang sudah pasti terjadi sejak zaman azali. Hal ini merupakan contoh dari...",
    "pilihan": {
      "A": "Qada",
      "B": "Qadar",
      "C": "Ikhtiar",
      "D": "Doa"
    },
    "kunci": "A"
  },
  {
    "no_soal": 28,
    "paket": "B",
    "soal": "Berkata atau memberikan informasi yang tidak sesuai dengan kenyataan yang sebenarnya disebut...",
    "pilihan": {
      "A": "Ghibah",
      "B": "Namimah",
      "C": "Bohong/Dusta",
      "D": "Fitnah"
    },
    "kunci": "C"
  },
  {
    "no_soal": 29,
    "paket": "B",
    "soal": "Cara bersuci untuk membersihkan diri dari hadas besar (seperti haid, nifas, atau junub) adalah dengan cara...",
    "pilihan": {
      "A": "Wudhu",
      "B": "Mandi Wajib",
      "C": "Tayamum",
      "D": "Membasuh muka"
    },
    "kunci": "B"
  },
  {
    "no_soal": 30,
    "paket": "B",
    "soal": "Allah SWT memberi rasa aman pada seluruh makhluk-Nya dan mengayomi hamba-hamba-Nya sehingga hidup tenteram. Hal ini karena Allah memiliki Asmaul Husna...",
    "pilihan": {
      "A": "Al-Mu'min",
      "B": "Al-Karim",
      "C": "Al-Wakil",
      "D": "Al-Matin"
    },
    "kunci": "A"
  },
  {
    "no_soal": 31,
    "paket": "B",
    "soal": "Al-Ashr adalah nama salah satu surat dalam Al-Qur'an. Arti dari kata Al-Ashr adalah...",
    "pilihan": {
      "A": "Matahari",
      "B": "Waktu/Masa",
      "C": "Gajah",
      "D": "Pertolongan"
    },
    "kunci": "B"
  },
  {
    "no_soal": 32,
    "paket": "B",
    "soal": "Allah SWT adalah Zat yang tersucikan dari segala macam kekurangan dan satu-satunya sembahan bagi semua makhluk. Asmaul Husna yang sesuai dengan pernyataan tersebut adalah...",
    "pilihan": {
      "A": "Al-Quddus",
      "B": "Al-Khaliq",
      "C": "Ar-Rahman",
      "D": "Al-Malik"
    },
    "kunci": "A"
  },
  {
    "no_soal": 33,
    "paket": "B",
    "soal": "Ketika kita tidak memahami apa yang telah dijelaskan oleh guru di kelas, maka sikap terbaik yang harus kita lakukan adalah...",
    "pilihan": {
      "A": "Diam saja karena takut",
      "B": "Pura-pura mengerti",
      "C": "Berani bertanya dengan sopan",
      "D": "Mengobrol dengan teman"
    },
    "kunci": "C"
  },
  {
    "no_soal": 34,
    "paket": "B",
    "soal": "Manakah di bawah ini yang merupakan lafal niat Shalat Tarawih (dua rakaat)?",
    "pilihan": {
      "A": "Ushalli sunnatal witri rak'ataini...",
      "B": "Ushalli sunnatat tahajjud rak'ataini...",
      "C": "Ushalli sunnatat tarawihi rak'ataini mustaqbilal qiblati adaa an lillahi ta'ala",
      "D": "Ushalli fardhol isya'i arba'a raka'atin..."
    },
    "kunci": "C"
  },
  {
    "no_soal": 35,
    "paket": "B",
    "soal": "Ali bin Abi Thalib mendapatkan gelar khusus karena keluasan ilmu pengetahuan yang dimilikinya. Gelar tersebut adalah...",
    "pilihan": {
      "A": "Saifullah (Pedang Allah)",
      "B": "Babul Ilmi (Pintu Ilmu)",
      "C": "Dzunnurain (Pemilik Dua Cahaya)",
      "D": "Al-Faruq (Pembeda)"
    },
    "kunci": "B"
  },
  {
    "no_soal": 36,
    "paket": "B",
    "soal": "Potongan ayat 'Fasabbih bihamdi rabbika wastaghfir innahu kaana tawwaaba' merupakan bunyi Surat An-Nashr ayat ke...",
    "pilihan": {
      "A": "Ke-1",
      "B": "Ke-2",
      "C": "Ke-3",
      "D": "Ke-4"
    },
    "kunci": "C"
  },
  {
    "no_soal": 37,
    "paket": "B",
    "soal": "Takdir Allah yang masih dapat diubah dengan usaha (ikhtiar) dan doa dari manusia disebut...",
    "pilihan": {
      "A": "Takdir Mubram",
      "B": "Takdir Muallaq",
      "C": "Sunnatullah",
      "D": "Nasib"
    },
    "kunci": "B"
  },
  {
    "no_soal": 38,
    "paket": "B",
    "soal": "Sikap merasa diri lebih baik dari orang lain dan meremehkan orang lain harus dijauhi. Dalam Islam, sikap sombong ini disebut...",
    "pilihan": {
      "A": "Takabur",
      "B": "Tawadhu",
      "C": "Qanaah",
      "D": "Husnuzan"
    },
    "kunci": "A"
  },
  {
    "no_soal": 39,
    "paket": "B",
    "soal": "Kondisi seperti Haid, Nifas, dan Jima' (hubungan suami istri) merupakan contoh penyebab seseorang berhadas...",
    "pilihan": {
      "A": "Kecil",
      "B": "Sedang",
      "C": "Besar",
      "D": "Ringan"
    },
    "kunci": "C"
  },
  {
    "no_soal": 40,
    "paket": "B",
    "soal": "Anak yang sudah balig disebut sebagai 'Mukallaf'. Arti dari Mukallaf adalah...",
    "pilihan": {
      "A": "Orang yang dibebaskan dari dosa",
      "B": "Orang dewasa yang wajib menjalankan hukum agama",
      "C": "Orang yang sedang menuntut ilmu",
      "D": "Orang yang belum diwajibkan shalat"
    },
    "kunci": "B"
  },
  {
    "no_soal": 41,
    "paket": "B",
    "soal": "Nabi Yusuf AS memiliki adik bernama Bunyamin dan 10 saudara tiri. Ibunya meninggal ketika beliau masih kecil. Siapakah nama Ibu kandung Nabi Yusuf AS?",
    "pilihan": {
      "A": "Siti Hajar",
      "B": "Siti Sarah",
      "C": "Siti Rahil (Rachel)",
      "D": "Siti Asiyah"
    },
    "kunci": "C"
  },
  {
    "no_soal": 42,
    "paket": "B",
    "soal": "Terjemahkan potongan ayat berikut: لَكُمْ دِينُكُمْ وَلِيَ دِينِ",
    "pilihan": {
      "A": "Bagiku pekerjaanku dan bagimu pekerjaanmu",
      "B": "Tidak ada paksaan dalam memeluk agama",
      "C": "Untukmu agamamu dan untukku agamaku",
      "D": "Sesungguhnya agama yang diridhai di sisi Allah hanyalah Islam"
    },
    "kunci": "C"
  },
  {
    "no_soal": 43,
    "paket": "B",
    "soal": "Shalat Sunnah yang dilaksanakan setahun sekali pada tanggal 10 Dzulhijjah disebut...",
    "pilihan": {
      "A": "Shalat Idul Fitri",
      "B": "Shalat Idul Adha",
      "C": "Shalat Istisqa",
      "D": "Shalat Gerhana"
    },
    "kunci": "B"
  },
  {
    "no_soal": 44,
    "paket": "B",
    "soal": "Nabi Musa a.s. diutus oleh Allah untuk memimpin dan menyelamatkan kaumnya dari penindasan Fir'aun. Kaum Nabi Musa tersebut disebut...",
    "pilihan": {
      "A": "Kaum 'Ad",
      "B": "Kaum Tsamud",
      "C": "Kaum Sodom",
      "D": "Bani Israil"
    },
    "kunci": "D"
  },
  {
    "no_soal": 45,
    "paket": "B",
    "soal": "Salah satu kewajiban setelah usia baligh adalah menutup aurat. Aurat bagi perempuan adalah seluruh tubuh, kecuali telapak tangan dan...",
    "pilihan": {
      "A": "Kaki",
      "B": "Rambut",
      "C": "Leher",
      "D": "Wajah"
    },
    "kunci": "D"
  },
  {
    "no_soal": 46,
    "paket": "B",
    "soal": "Sahabat Nabi Muhammad SAW yang terkenal memiliki suara sangat merdu dan dipercaya sebagai muadzin pertama dalam Islam adalah...",
    "pilihan": {
      "A": "Abu Hurairah",
      "B": "Bilal bin Rabah",
      "C": "Zaid bin Tsabit",
      "D": "Salman Al-Farisi"
    },
    "kunci": "B"
  },
  {
    "no_soal": 47,
    "paket": "B",
    "soal": "Terjemahkan potongan ayat berikut: وَتَعَاوَنُوا عَلَى الْبِرِّ وَالتَّقْوَى",
    "pilihan": {
      "A": "Berlomba-lombalah dalam kebaikan",
      "B": "Dan tolong-menolonglah kamu dalam (mengerjakan) kebajikan dan takwa",
      "C": "Dan janganlah kamu tolong-menolong dalam berbuat dosa",
      "D": "Sesungguhnya Allah menyukai orang-orang yang berbuat baik"
    },
    "kunci": "B"
  },
  {
    "no_soal": 48,
    "paket": "B",
    "soal": "Shalat sunnah yang dilakukan secara khusus pada setiap malam di bulan Ramadhan setelah shalat Isya disebut...",
    "pilihan": {
      "A": "Shalat Witir",
      "B": "Shalat Tahajud",
      "C": "Shalat Tarawih",
      "D": "Shalat Iftitah"
    },
    "kunci": "C"
  },
  {
    "no_soal": 49,
    "paket": "B",
    "soal": "Nabi Luth a.s. diutus Allah untuk mengajak kaumnya menjauhi perilaku menyimpang (menyukai sesama jenis). Kaum Nabi Luth yang dibinasakan Allah tersebut dikenal dengan nama...",
    "pilihan": {
      "A": "Kaum 'Ad",
      "B": "Kaum Madinah",
      "C": "Kaum Saba'",
      "D": "Kaum Sodom (Sadum)"
    },
    "kunci": "D"
  },
  {
    "no_soal": 50,
    "paket": "B",
    "soal": "Mengucapkan salam hukumnya adalah sunnah, namun bagi orang yang mendengarnya, hukum menjawab salam adalah...",
    "pilihan": {
      "A": "Sunnah Muakkad",
      "B": "Mubah",
      "C": "Wajib",
      "D": "Makruh"
    },
    "kunci": "C"
  },
  {
    "no_soal": 51,
    "paket": "B",
    "soal": "Salah satu ciri orang munafik menurut hadits Nabi adalah apabila ia berkata maka ia...",
    "pilihan": {
      "A": "Jujur",
      "B": "Menepati",
      "C": "Berdusta",
      "D": "Amanah"
    },
    "kunci": "C"
  },
  {
    "no_soal": 52,
    "paket": "B",
    "soal": "Terjemahkan ayat berikut ini: إِنَّ شَانِئَكَ هُوَ الْابْتَرُ",
    "pilihan": {
      "A": "Sesungguhnya Kami telah memberikan kepadamu nikmat yang banyak",
      "B": "Maka dirikanlah shalat karena Tuhanmu dan berkorbanlah",
      "C": "Sesungguhnya orang-orang yang membencimu dialah yang terputus (dari rahmat Allah)",
      "D": "Dari kejahatan (bisikan) syaitan yang biasa bersembunyi"
    },
    "kunci": "C"
  },
  {
    "no_soal": 53,
    "paket": "B",
    "soal": "Shalat Dhuha adalah shalat sunnah yang dianjurkan oleh agama sebagai tambahan atau penyempurna shalat fardhu. Hukum melaksanakan Shalat Dhuha adalah...",
    "pilihan": {
      "A": "Fardhu 'Ain",
      "B": "Fardhu Kifayah",
      "C": "Sunnah Muakkad",
      "D": "Sunnah Ghairu Muakkad"
    },
    "kunci": "C"
  },
  {
    "no_soal": 54,
    "paket": "B",
    "soal": "Nabi Hud a.s. diutus oleh Allah SWT untuk menyeru kaumnya agar menyembah Allah. Kaum Nabi Hud tersebut dikenal dengan sebutan...",
    "pilihan": {
      "A": "Kaum Tsamud",
      "B": "Kaum 'Ad",
      "C": "Kaum Sodom",
      "D": "Kaum Quraisy"
    },
    "kunci": "B"
  },
  {
    "no_soal": 55,
    "paket": "B",
    "soal": "Mengucapkan salam kepada sesama muslim merupakan perbuatan terpuji. Dalam Islam, kalimat salam dan doa-doa baik lainnya termasuk ke dalam golongan kalimat...",
    "pilihan": {
      "A": "Kalimat Syahadat",
      "B": "Kalimat Thoyyibah",
      "C": "Kalimat Tarji'",
      "D": "Kalimat Tasbih"
    },
    "kunci": "B"
  },
  {
    "no_soal": 56,
    "paket": "B",
    "soal": "Salah satu mukjizat nabi adalah kemampuannya menafsirkan mimpi dengan tepat, seperti menafsirkan mimpi raja Mesir tentang 7 sapi kurus memakan 7 sapi gemuk. Nabi tersebut adalah...",
    "pilihan": {
      "A": "Nabi Ibrahim a.s.",
      "B": "Nabi Musa a.s.",
      "C": "Nabi Yusuf a.s.",
      "D": "Nabi Daud a.s."
    },
    "kunci": "C"
  },
  {
    "no_soal": 57,
    "paket": "B",
    "soal": "Terjemahkan potongan ayat berikut: مِنَ الْجِنَّةِ وَالنَّاسِ",
    "pilihan": {
      "A": "Katakanlah: Aku berlindung kepada Tuhan (yang memelihara dan menguasai) manusia",
      "B": "Raja manusia",
      "C": "Dari kejahatan (bisikan) syaitan yang biasa bersembunyi",
      "D": "Dari golongan jin dan manusia"
    },
    "kunci": "D"
  },
  {
    "no_soal": 58,
    "paket": "B",
    "soal": "Berdiam diri untuk memperbanyak dzikir dan doa di Padang Arafah pada tanggal 9 Dzulhijjah mulai dari tergelincir matahari sampai terbenam matahari disebut...",
    "pilihan": {
      "A": "Thawaf",
      "B": "Sa'i",
      "C": "Wukuf",
      "D": "Mabit"
    },
    "kunci": "C"
  },
  {
    "no_soal": 59,
    "paket": "B",
    "soal": "Ketika seseorang memasuki usia baligh (dewasa), ia disebut mukallaf dan mulai menanggung dosa sendiri. Kewajiban paling utama yang harus dijalankan adalah...",
    "pilihan": {
      "A": "Bekerja mencari nafkah",
      "B": "Menikah",
      "C": "Pergi Haji",
      "D": "Melaksanakan Shalat Fardhu"
    },
    "kunci": "D"
  },
  {
    "no_soal": 60,
    "paket": "B",
    "soal": "Lanjutkan ayat berikut ini: مَا وَدَّعَكَ رَبُّكَ وَمَا قَلَى ...",
    "pilihan": {
      "A": "Wadh dhuhaa",
      "B": "Walal aakhiratu khairul laka minal uula",
      "C": "Wa la sawfa yu'tika rabbuka fatardha",
      "D": "Alam yajidka yatiiman fa aawa"
    },
    "kunci": "B"
  },
  {
    "no_soal": 1,
    "paket": "C",
    "soal": "Apa arti ayat berikut! إِنَّ أَكْرَمَكُمْ عِنْدَ اللَّهِ أَتْقُكُمْ",
    "pilihan": {
      "A": "Sesungguhnya orang yang paling kaya di antara kamu adalah yang paling dermawan",
      "B": "Sesungguhnya yang paling mulia di antara kamu di sisi Allah ialah orang yang paling bertakwa",
      "C": "Wahai manusia, sesungguhnya Kami menciptakan kamu dari seorang laki-laki dan seorang perempuan",
      "D": "Sesungguhnya Allah Maha Mengetahui lagi Maha Mengenal"
    },
    "kunci": "B"
  },
  {
    "no_soal": 2,
    "paket": "C",
    "soal": "Perhatikan ayat berikut! وَوَجَدَكَ عَابِلًا فَاغْلى . Bacaan Mad Wajib Muttasil pada ayat tersebut dibaca panjang sebanyak...",
    "pilihan": {
      "A": "2 harakat",
      "B": "2-4 harakat",
      "C": "4-6 harakat",
      "D": "6 harakat mutlak"
    },
    "kunci": "C"
  },
  {
    "no_soal": 3,
    "paket": "C",
    "soal": "Perhatikan ayat berikut! يَأَيُّهَا الَّذِينَ ءَامَنُوا اجْتَنِبُوا كَثِيرًا مِّنَ الظَّنِّ إِنَّ بَعْضَ الظَّنِّ إِثْم . Perbuatan apa yang dilarang dalam ayat tersebut?",
    "pilihan": {
      "A": "Ghibah (Menggunjing)",
      "B": "Namimah (Adu Domba)",
      "C": "Berprasangka buruk (Suudzon)",
      "D": "Sombong (Takabur)"
    },
    "kunci": "C"
  },
  {
    "no_soal": 4,
    "paket": "C",
    "soal": "Siapkan alat tulis! Pak Agus mempunyai seorang isteri, 3 orang anak laki-laki, dan 3 anak perempuan. Berapa kg beras yang harus dikeluarkan Pak Agus untuk membayar zakat fitrah untuk seluruh keluarganya? (Asumsi 1 orang = 2,5 kg)",
    "pilihan": {
      "A": "17,5 kg beras",
      "B": "20 kg beras",
      "C": "22,5 kg beras",
      "D": "25 kg beras"
    },
    "kunci": "B"
  },
  {
    "no_soal": 5,
    "paket": "C",
    "soal": "Berita gembira yang dikabarkan dalam Surah An-Nasr ialah bahwa Rasulullah SAW dan umat Islam akan memperoleh...",
    "pilihan": {
      "A": "Harta rampasan perang",
      "B": "Kemenangan dan pertolongan Allah",
      "C": "Wahyu Al-Qur'an",
      "D": "Kekuasaan di seluruh dunia"
    },
    "kunci": "B"
  },
  {
    "no_soal": 6,
    "paket": "C",
    "soal": "Allah SWT mampu melindungi tiap-tiap manusia dari segala hal yang mungkin mengusiknya, karena Allah SWT Maha Memberi Keamanan. Asmaul Husna yang sesuai adalah...",
    "pilihan": {
      "A": "Al-Mukmin",
      "B": "Al-Muhaimin",
      "C": "Al-Matin",
      "D": "Al-Wakil"
    },
    "kunci": "A"
  },
  {
    "no_soal": 7,
    "paket": "C",
    "soal": "Sahabat Nabi Muhammad SAW yang menggantikan posisi beliau tidur di kamarnya ketika akan berangkat hijrah dengan tujuan mengelabui kaum kafir Quraisy adalah...",
    "pilihan": {
      "A": "Abu Bakar Ash-Shiddiq",
      "B": "Umar bin Khattab",
      "C": "Utsman bin Affan",
      "D": "Ali bin Abi Thalib"
    },
    "kunci": "D"
  },
  {
    "no_soal": 8,
    "paket": "C",
    "soal": "Perhatikan ayat berikut: وَالهُكُمْ إِلَهٌ وَاحِدٌ لَا إِلَهَ إِلَّا هُوَ الرَّحْمَنُ الرَّحِيمُ . Apa arti kata 'Wahid' yang terdapat pada ayat tersebut?",
    "pilihan": {
      "A": "Allah Maha Pengasih",
      "B": "Allah Maha Penyayang",
      "C": "Allah Dzat Tunggal/Maha Esa",
      "D": "Allah Maha Perkasa"
    },
    "kunci": "C"
  },
  {
    "no_soal": 9,
    "paket": "C",
    "soal": "Dalam pembagian zakat, terdapat istilah 'Amil'. Apa yang dimaksud dengan Amil?",
    "pilihan": {
      "A": "Orang yang baru masuk Islam",
      "B": "Orang yang berhutang untuk kebaikan",
      "C": "Orang yang dalam perjalanan jauh",
      "D": "Pihak yang bertanggung jawab mengelola zakat"
    },
    "kunci": "D"
  },
  {
    "no_soal": 10,
    "paket": "C",
    "soal": "Segala sesuatu yang mengakibatkan pelakunya mendapat dosa, atau segala sesuatu yang menjurus kepada keburukan jika dilakukan, disebut dengan hukum...",
    "pilihan": {
      "A": "Makruh",
      "B": "Haram",
      "C": "Mubah",
      "D": "Syubhat"
    },
    "kunci": "B"
  },
  {
    "no_soal": 11,
    "paket": "C",
    "soal": "Apa arti dari potongan ayat berikut ini: وَالضُّحَى وَالْلَّيْلِ إِذَا سَجَى",
    "pilihan": {
      "A": "Demi waktu matahari sepenggalah naik",
      "B": "Dan demi malam apabila telah sunyi/gelap",
      "C": "Demi masa, sesungguhnya manusia dalam kerugian",
      "D": "Dan demi negeri yang aman ini"
    },
    "kunci": "B"
  },
  {
    "no_soal": 12,
    "paket": "C",
    "soal": "Allah mampu mengetahui perbuatan manusia walau sembunyi-sembunyi, serta mengetahui apa yang tersimpan di dalam hati meskipun tidak diucapkan. Pernyataan tersebut merupakan makna Asmaul Husna...",
    "pilihan": {
      "A": "Al-Khabir",
      "B": "Al-Basir",
      "C": "Al-'Alim",
      "D": "As-Sami'"
    },
    "kunci": "C"
  },
  {
    "no_soal": 13,
    "paket": "C",
    "soal": "Perhatikan ayat: وَلَا يَغْتَب بَعْضُكُم بَعْضًا أَيُحِبُّ أَحَدُكُمْ أَن يَأْكُلَ لَحْمَ أَخِيهِ مَيْتًا . Ayat tersebut melarang manusia melakukan perbuatan...",
    "pilihan": {
      "A": "Fitnah",
      "B": "Ghibah (Menggunjing)",
      "C": "Hasad (Dengki)",
      "D": "Namimah (Adu Domba)"
    },
    "kunci": "B"
  },
  {
    "no_soal": 14,
    "paket": "C",
    "soal": "Siapkan alat tulis! Bapak Abdul mempunyai seorang isteri, 3 orang anak laki-laki, 3 orang anak perempuan, serta Ibu dan Ayahnya yang sudah tua renta dan tinggal bersamanya. Berapa kg beras yang harus dikeluarkan Pak Abdul untuk zakat fitrah seluruhnya?",
    "pilihan": {
      "A": "20 kg",
      "B": "22,5 kg",
      "C": "25 kg",
      "D": "27,5 kg"
    },
    "kunci": "C"
  },
  {
    "no_soal": 15,
    "paket": "C",
    "soal": "Allah itu Maha Esa, tidak beranak dan tidak diperanakkan. Hal ini disebutkan dengan tegas dalam Al-Qur'an surat...",
    "pilihan": {
      "A": "Al-Fatihah",
      "B": "An-Nas",
      "C": "Al-Kafirun",
      "D": "Al-Ikhlas"
    },
    "kunci": "D"
  },
  {
    "no_soal": 16,
    "paket": "C",
    "soal": "Tokoh pembesar kafir Quraisy yang akhirnya menyatakan diri masuk Islam pada saat peristiwa Fathu Makkah adalah...",
    "pilihan": {
      "A": "Abu Lahab",
      "B": "Abu Jahal",
      "C": "Abu Sufyan bin Harb",
      "D": "Ikrimah bin Abu Jahal"
    },
    "kunci": "C"
  },
  {
    "no_soal": 17,
    "paket": "C",
    "soal": "Perjanjian damai yang dilakukan Nabi Muhammad SAW dengan para pembesar Quraisy pada tahun ke-6 Hijrah yang menjadi titik balik diplomasi Islam adalah...",
    "pilihan": {
      "A": "Perjanjian Aqabah",
      "B": "Piagam Madinah",
      "C": "Perjanjian Hudaibiyah",
      "D": "Perjanjian Daumatul Jandal"
    },
    "kunci": "C"
  },
  {
    "no_soal": 18,
    "paket": "C",
    "soal": "Perhatikan potongan ayat Kursi berikut: اللَّهُ لَا إِلَهَ إِلَّا هُوَ الْحَيُّ الْقَيُّومُ . Apa arti Asmaul Husna 'Al-Qayyum' pada ayat tersebut?",
    "pilihan": {
      "A": "Maha Hidup Kekal",
      "B": "Maha Berdiri Sendiri / Mandiri",
      "C": "Maha Mengetahui",
      "D": "Maha Agung"
    },
    "kunci": "B"
  },
  {
    "no_soal": 19,
    "paket": "C",
    "soal": "Dalam pembagian zakat, salah satu asnaf (golongan penerima) adalah Fisabilillah. Apa yang dimaksud dengan Fisabilillah?",
    "pilihan": {
      "A": "Orang yang kehabisan bekal perjalanan",
      "B": "Orang yang terlilit hutang",
      "C": "Budak yang ingin memerdekakan diri",
      "D": "Orang yang berjuang di jalan Allah"
    },
    "kunci": "D"
  },
  {
    "no_soal": 20,
    "paket": "C",
    "soal": "Kejujuran adalah pondasi kepercayaan. Berikut ini yang merupakan akibat buruk bagi orang yang tidak jujur adalah...",
    "pilihan": {
      "A": "Disenangi banyak teman",
      "B": "Hati menjadi tenang",
      "C": "Tidak dipercaya dan hati gelisah",
      "D": "Mendapat kemudahan urusan"
    },
    "kunci": "C"
  },
  {
    "no_soal": 21,
    "paket": "C",
    "soal": "Apa arti ayat berikut ini: وَلَا أَنَا عَابِدُ مَّا عُبَدْتُمْ",
    "pilihan": {
      "A": "Dan kamu bukan penyembah Tuhan yang aku sembah",
      "B": "Dan aku bukan penyembah apa yang kamu sembah",
      "C": "Untukmu agamamu dan untukku agamaku",
      "D": "Aku tidak akan menyembah apa yang kamu sembah"
    },
    "kunci": "B"
  },
  {
    "no_soal": 22,
    "paket": "C",
    "soal": "Allah SWT adalah satu-satunya tempat manusia bersandar dan meminta. Allah SWT Maha dibutuhkan oleh semua makhluk-Nya. Asmaul Husna yang sesuai dengan pernyataan tersebut ialah...",
    "pilihan": {
      "A": "Al-Ahad",
      "B": "As-Samad",
      "C": "Al-Muqtadir",
      "D": "Al-Baqi"
    },
    "kunci": "B"
  },
  {
    "no_soal": 23,
    "paket": "C",
    "soal": "Perhatikan kutipan ayat berikut: وَتَعَاوَنُوا عَلَى الْبِرِّ وَالتَّقْوَى . Apa yang diperintahkan dalam ayat tersebut?",
    "pilihan": {
      "A": "Berlomba-lomba dalam kebaikan",
      "B": "Tolong menolong dalam dosa",
      "C": "Tolong menolong dalam kebaikan dan takwa",
      "D": "Saling menasihati dalam kesabaran"
    },
    "kunci": "C"
  },
  {
    "no_soal": 24,
    "paket": "C",
    "soal": "Siapkan alat tulis! Bapak Junaedi mempunyai 2 orang anak laki-laki dan 3 anak perempuan. Pada waktu itu harga beras Rp 12.000,- per Kg. Berapa rupiah jumlah uang yang harus dikeluarkan Pak Junaedi untuk zakat fitrah (bagi dirinya dan anak-anaknya)?",
    "pilihan": {
      "A": "Rp 150.000",
      "B": "Rp 180.000",
      "C": "Rp 210.000",
      "D": "Rp 225.000"
    },
    "kunci": "B"
  },
  {
    "no_soal": 25,
    "paket": "C",
    "soal": "Dalam kehidupan bermasyarakat kita harus saling menghargai perbedaan pendapat, agama, keyakinan, dan tradisi yang ada. Sikap saling menghargai tersebut dikenal dengan istilah...",
    "pilihan": {
      "A": "Tawadhu",
      "B": "Toleransi (Tasamuh)",
      "C": "Qanaah",
      "D": "Husnuzan"
    },
    "kunci": "B"
  },
  {
    "no_soal": 26,
    "paket": "C",
    "soal": "Terdapat beberapa Nabi dan Rasul yang memiliki keistimewaan berupa ketabahan luar biasa, yang disebut Ulul Azmi. Berikut ini yang merupakan 5 Rasul Ulul Azmi adalah...",
    "pilihan": {
      "A": "Nabi Adam, Nabi Nuh, Nabi Ibrahim, Nabi Musa, Nabi Muhammad",
      "B": "Nabi Nuh, Nabi Ibrahim, Nabi Musa, Nabi Isa, Nabi Muhammad",
      "C": "Nabi Nuh, Nabi Ibrahim, Nabi Ismail, Nabi Isa, Nabi Muhammad",
      "D": "Nabi Ibrahim, Nabi Musa, Nabi Daud, Nabi Sulaiman, Nabi Isa"
    },
    "kunci": "B"
  },
  {
    "no_soal": 27,
    "paket": "C",
    "soal": "Setiap Nabi memiliki silsilah keluarga. Siapakah nama ayah dari Nabi Yunus a.s.?",
    "pilihan": {
      "A": "Azar",
      "B": "Imran",
      "C": "Matta",
      "D": "Tarikh"
    },
    "kunci": "C"
  },
  {
    "no_soal": 28,
    "paket": "C",
    "soal": "Perhatikan ayat berikut: اللَّهُ خَالِقُ كُلِّ شَيْءٍ وَهُوَ الْعَزِيزُ الْحَكِيمُ . Apa arti Asmaul Husna 'Al-Khaliq' pada ayat tersebut?",
    "pilihan": {
      "A": "Maha Bijaksana",
      "B": "Maha Perkasa",
      "C": "Maha Pencipta",
      "D": "Maha Memelihara"
    },
    "kunci": "C"
  },
  {
    "no_soal": 29,
    "paket": "C",
    "soal": "Salah satu golongan penerima zakat adalah Ibnu Sabil. Apa yang dimaksud dengan Ibnu Sabil?",
    "pilihan": {
      "A": "Orang yang banyak hutangnya",
      "B": "Orang yang miskin",
      "C": "Panitia zakat",
      "D": "Orang yang sedang dalam perjalanan (musafir)"
    },
    "kunci": "D"
  },
  {
    "no_soal": 30,
    "paket": "C",
    "soal": "Kesediaan melaksanakan kewajiban dengan sadar dan sungguh-sungguh serta berani menanggung segala risikonya disebut...",
    "pilihan": {
      "A": "Tanggung jawab",
      "B": "Disiplin",
      "C": "Jujur",
      "D": "Kerja keras"
    },
    "kunci": "A"
  },
  {
    "no_soal": 31,
    "paket": "C",
    "soal": "Apa arti ayat berikut? لَكُمْ دِينُكُمْ وَلِيَ دِينِ",
    "pilihan": {
      "A": "Bagiku pekerjaanku dan bagimu pekerjaanmu",
      "B": "Sesungguhnya agama yang diridhai Allah adalah Islam",
      "C": "Untukmu agamamu dan untukku agamaku",
      "D": "Tidak ada paksaan dalam memeluk agama"
    },
    "kunci": "C"
  },
  {
    "no_soal": 32,
    "paket": "C",
    "soal": "Gunung-gunung yang menjulang tinggi, sungai yang mengalir, serta hamparan laut yang luas, semua diatur oleh kekuasaan Allah SWT. Pernyataan tersebut merupakan makna Asmaul Husna...",
    "pilihan": {
      "A": "Al-Muqtadir",
      "B": "Al-Khaliq",
      "C": "Al-Musawwir",
      "D": "Al-Wahhab"
    },
    "kunci": "A"
  },
  {
    "no_soal": 33,
    "paket": "C",
    "soal": "Perhatikan kutipan ayat berikut: وَلَا تَعَاوَنُوا عَلَى الْإِثْمِ وَالْعُدْوَانِ . Apa yang dilarang dalam ayat tersebut?",
    "pilihan": {
      "A": "Jangan tolong menolong dalam kebaikan",
      "B": "Jangan tolong menolong dalam perbuatan dosa dan permusuhan",
      "C": "Jangan memakan harta anak yatim",
      "D": "Jangan berbuat kerusakan di muka bumi"
    },
    "kunci": "B"
  },
  {
    "no_soal": 34,
    "paket": "C",
    "soal": "Siapkan alat tulis! Bapak Umar mempunyai seorang isteri, 1 orang anak laki-laki, dan 1 anak angkat perempuan. Pada waktu itu harga beras Rp 13.000,- per Kg. Berapa rupiah jumlah uang yang harus dikeluarkan Pak Umar untuk membayar zakat fitrah bagi seluruh keluarganya?",
    "pilihan": {
      "A": "Rp 97.500,-",
      "B": "Rp 110.000,-",
      "C": "Rp 130.000,-",
      "D": "Rp 162.500,-"
    },
    "kunci": "C"
  },
  {
    "no_soal": 35,
    "paket": "C",
    "soal": "Kepedulian dan ikut merasakan apa yang dirasakan orang lain dapat menumbuhkan rasa saling mengasihi. Sikap ikut merasakan penderitaan orang lain ini disebut...",
    "pilihan": {
      "A": "Jujur",
      "B": "Simpati",
      "C": "Optimis",
      "D": "Tawakal"
    },
    "kunci": "B"
  },
  {
    "no_soal": 36,
    "paket": "C",
    "soal": "Pada hari kiamat, Allah SWT menugaskan malaikat untuk meniup sangkakala yang dapat menghancurkan alam semesta. Malaikat tersebut adalah...",
    "pilihan": {
      "A": "Jibril",
      "B": "Mikail",
      "C": "Izrail",
      "D": "Israfil"
    },
    "kunci": "D"
  },
  {
    "no_soal": 37,
    "paket": "C",
    "soal": "Salah satu istri Rasulullah SAW bernama Hafshah. Beliau adalah putri dari sahabat Rasulullah yang bernama...",
    "pilihan": {
      "A": "Abu Bakar Ash-Shiddiq",
      "B": "Umar bin Khattab",
      "C": "Utsman bin Affan",
      "D": "Ali bin Abi Thalib"
    },
    "kunci": "B"
  },
  {
    "no_soal": 38,
    "paket": "C",
    "soal": "Perhatikan potongan ayat berikut: تَنْزِيلُ الْكِتَابِ مِنَ اللَّهِ الْعَزِيزُ الْحَكِيمُ . Apa arti Asmaul Husna 'Al-Hakim' pada ayat tersebut?",
    "pilihan": {
      "A": "Maha Perkasa",
      "B": "Maha Mengetahui",
      "C": "Maha Bijaksana",
      "D": "Maha Pengampun"
    },
    "kunci": "C"
  },
  {
    "no_soal": 39,
    "paket": "C",
    "soal": "Hari kiamat memiliki banyak nama lain sesuai dengan kejadiannya. Nama lain 'Yaumul Jaza' berarti...",
    "pilihan": {
      "A": "Hari Perhitungan",
      "B": "Hari Kebangkitan",
      "C": "Hari Berkumpul",
      "D": "Hari Pembalasan"
    },
    "kunci": "D"
  },
  {
    "no_soal": 40,
    "paket": "C",
    "soal": "Dalam hadits riwayat Abu Daud, sifat hasud (dengki) itu berbahaya karena dapat menghilangkan/memakan kebaikan ibarat...",
    "pilihan": {
      "A": "Air memadamkan api",
      "B": "Api memakan kayu bakar",
      "C": "Panas melelehkan lilin",
      "D": "Angin menerbangkan debu"
    },
    "kunci": "B"
  },
  {
    "no_soal": 41,
    "paket": "C",
    "soal": "Perhatikan ayat berikut! أَرَأَيْتَ الَّذِي يُكَذِّبُ بِالدِّينِ . Terjemahan ayat tersebut adalah...",
    "pilihan": {
      "A": "Maka itulah orang yang menghardik anak yatim",
      "B": "Tahukah kamu (orang) yang mendustakan agama?",
      "C": "Celakalah bagi orang-orang yang shalat",
      "D": "Sesungguhnya Kami telah memberikan nikmat yang banyak"
    },
    "kunci": "B"
  },
  {
    "no_soal": 42,
    "paket": "C",
    "soal": "Meyakini bahwa Rasul adalah utusan Allah yang membawa ajaran untuk membimbing umat manusia merupakan makna dari beriman kepada...",
    "pilihan": {
      "A": "Malaikat Allah",
      "B": "Kitab Allah",
      "C": "Rasul Allah",
      "D": "Hari Akhir"
    },
    "kunci": "C"
  },
  {
    "no_soal": 43,
    "paket": "C",
    "soal": "Lafal doa taubat Nabi Yunus a.s. yang dibaca ketika berada di dalam perut ikan paus adalah...",
    "pilihan": {
      "A": "Rabbana zholamna anfusana wa illam taghfir lana...",
      "B": "La ilaha illa anta subhanaka inni kuntu minazh zhalimin",
      "C": "Rabbi ishrah li sadri wa yassir li amri",
      "D": "Rabbana atina fid dunya hasanah"
    },
    "kunci": "B"
  },
  {
    "no_soal": 44,
    "paket": "C",
    "soal": "Dalam Islam, segala aturan hidup memiliki landasan. Sumber utama hukum halal dan haram adalah...",
    "pilihan": {
      "A": "Al-Qur'an",
      "B": "Ijtihad Ulama",
      "C": "Qiyas",
      "D": "Adat Istiadat"
    },
    "kunci": "A"
  },
  {
    "no_soal": 45,
    "paket": "C",
    "soal": "Abu Bakar mendapat gelar 'As-Siddiq' dari Rasulullah SAW karena beliau adalah orang yang pertama kali membenarkan peristiwa...",
    "pilihan": {
      "A": "Turunnya wahyu pertama",
      "B": "Hijrah ke Madinah",
      "C": "Isra' Mi'raj",
      "D": "Perang Badar"
    },
    "kunci": "C"
  },
  {
    "no_soal": 46,
    "paket": "C",
    "soal": "Pemberian dari seorang muslim kepada orang lain secara sukarela dan ikhlas berupa harta, benda, atau jasa dengan hanya memohon ridha Allah disebut...",
    "pilihan": {
      "A": "Zakat",
      "B": "Pajak",
      "C": "Sedekah",
      "D": "Fidyah"
    },
    "kunci": "C"
  },
  {
    "no_soal": 47,
    "paket": "C",
    "soal": "Dalam gerakan shalat, posisi duduk di antara dua sujud disebut dengan duduk...",
    "pilihan": {
      "A": "Tawarruk",
      "B": "Iftirasy",
      "C": "Bersila",
      "D": "Masbuk"
    },
    "kunci": "B"
  },
  {
    "no_soal": 48,
    "paket": "C",
    "soal": "Banyak surat dalam Al-Qur'an yang menggunakan nama hewan. Manakah di bawah ini yang merupakan kumpulan surat dengan nama hewan?",
    "pilihan": {
      "A": "Al-Baqarah, An-Nas, Al-Falaq, An-Nahl",
      "B": "Al-Baqarah, Al-Fil, An-Nahl, Al-Ankabut",
      "C": "Al-Fil, Al-Maun, Al-Kautsar, An-Naml",
      "D": "An-Nahl, Al-Ankabut, Yasin, Al-Waqiah"
    },
    "kunci": "B"
  },
  {
    "no_soal": 49,
    "paket": "C",
    "soal": "Manakah lafal niat shalat Subuh yang tepat bagi seorang makmum?",
    "pilihan": {
      "A": "Ushalli fardhas subhi rak'ataini mustaqbilal qiblati adaa-an lillahi ta'ala",
      "B": "Ushalli fardhas subhi rak'ataini mustaqbilal qiblati adaa-an imaman lillahi ta'ala",
      "C": "Ushalli fardhas subhi rak'ataini mustaqbilal qiblati adaa-an ma'muman lillahi ta'ala",
      "D": "Ushalli sunnatas subhi rak'ataini mustaqbilal qiblati lillahi ta'ala"
    },
    "kunci": "C"
  },
  {
    "no_soal": 50,
    "paket": "C",
    "soal": "Dalam ilmu Tajwid, huruf Mad Thabi'i (Mad Asli) berjumlah tiga, yaitu...",
    "pilihan": {
      "A": "Alif (ا), Wau (و), Ya (ي)",
      "B": "Nun (ن), Mim (م), Wau (و)",
      "C": "Lam (ل), Ra (ر)",
      "D": "Hamzah (ء), Ha (ه), Kho (خ)"
    },
    "kunci": "A"
  },
  {
    "no_soal": 51,
    "paket": "C",
    "soal": "Huruf-huruf Idzhar Halqi berjumlah 6. Berikut ini yang termasuk huruf Idzhar adalah...",
    "pilihan": {
      "A": "Ba (ب)",
      "B": "Ya (ي), Nun (ن), Mim (م), Wau (و)",
      "C": "Hamzah (ء), Ha (ه), Ain (ع), Ghain (غ), Ha (ح), Kho (خ)",
      "D": "Lam (ل), Ra (ر)"
    },
    "kunci": "C"
  },
  {
    "no_soal": 52,
    "paket": "C",
    "soal": "Siapkan alat tulis! Ustadz Ahmad mempunyai seorang istri, 2 orang anak laki-laki, dan 4 anak perempuan. Jika zakat fitrah dibayar dengan beras (2,5 kg per jiwa), berapa total beras yang harus dikeluarkan?",
    "pilihan": {
      "A": "15 Kg",
      "B": "17,5 Kg",
      "C": "20 Kg",
      "D": "25 Kg"
    },
    "kunci": "C"
  },
  {
    "no_soal": 53,
    "paket": "C",
    "soal": "Setelah diturunkan ke bumi di tempat yang terpisah jauh, Nabi Adam a.s. dan Siti Hawa akhirnya bertemu kembali di suatu tempat yang bernama...",
    "pilihan": {
      "A": "Jabal Nur",
      "B": "Jabal Tsur",
      "C": "Jabal Rahmah (Padang Arafah)",
      "D": "Bukit Safa"
    },
    "kunci": "C"
  },
  {
    "no_soal": 54,
    "paket": "C",
    "soal": "Penduduk Madinah yang memeluk Islam dan membantu kaum Muhajirin yang hijrah dari Mekkah disebut dengan kaum...",
    "pilihan": {
      "A": "Muhajirin",
      "B": "Anshar",
      "C": "Musyrikin",
      "D": "Badui"
    },
    "kunci": "B"
  },
  {
    "no_soal": 55,
    "paket": "C",
    "soal": "Nabi yang dikenal sebagai 'Khatibul Anbiya' (Ahli pidato para Nabi), melarang kaumnya berbuat curang dalam timbangan dan takaran, adalah...",
    "pilihan": {
      "A": "Nabi Luth a.s.",
      "B": "Nabi Saleh a.s.",
      "C": "Nabi Syu'aib a.s.",
      "D": "Nabi Hud a.s."
    },
    "kunci": "C"
  }
]